redditmemeapi
