Metadata-Version: 2.1
Name: redditmemeapi
Version: 0.0.2
Summary: A pythonic API wrapper to fetch memes from https://meme-api.com
Home-page: https://github.com/therealcyber71/redditmemeapi
Author: thereal_cyber
Author-email: quantechlxxi.corp@gmail.com
License: MIT
Project-URL: APIs, https://github.com/therealcyber71/redditmemeapi/issues
Keywords: memes,api,discord,telegram
Platform: UNKNOWN
Classifier: Development Status :: 3 - Alpha
Classifier: Intended Audience :: Developers
Classifier: License :: OSI Approved :: MIT License
Classifier: Programming Language :: Python :: 3
Classifier: Programming Language :: Python :: 3.7
Classifier: Programming Language :: Python :: 3.8
Classifier: Programming Language :: Python :: 3.9
License-File: LICENSE.md
